LocalAugment/__init__.py
local_augment-0.1.8.dist-info/LICENSE
local_augment-0.1.8.dist-info/METADATA
local_augment-0.1.8.dist-info/WHEEL
local_augment-0.1.8.dist-info/top_level.txt
local_augment-0.1.8.dist-info/RECORD
