Metadata-Version: 2.1
Name: local-augment
Version: 0.1.8
Summary: A package for local data augmentation in deep learning
Home-page: https://github.com/dream-oyh/LocalAugment
Author: TayDream
Author-email: 19859860010@163.com
License: MIT license
Classifier: Programming Language :: Python :: 3
Classifier: License :: OSI Approved :: MIT License
Classifier: Operating System :: OS Independent
License-File: LICENSE
